{"SpecPriv": true, "Edge": true, "Loop": true, "LAMP": true, "Experiment": {"speedup": 16.39, "loops": {"_Z6workerPv :: for.cond37.i198.i": {"covered_lcDeps": 10, "loop_speedup": 3.13, "total_time": 427, "dependence_info": {"num_waw_lcdep": 0, "num_control_lcdep": 10, "num_reg_lcdep": 1, "chosen_count": {"reg": {"replicable-stage-remedy": 1}, "ctrl": {"replicable-stage-remedy": 0, "ctrl-spec-remedy": 10}, "raw": {}, "waw": {}, "war": {}}, "num_war_lcdep": 0, "num_queries": 9, "num_raw_lcdep": 0, "avail_count": {"reg": {"replicable-stage-remedy": 1}, "ctrl": {"replicable-stage-remedy": 0, "ctrl-spec-remedy": 10}, "raw": {}, "waw": {}, "war": {}}}, "total_lcDeps": 11, "loop_stage": "DSWP[P22']", "lcDeps_coverage": 90.91, "debug_info": "filename:HJM.cpp, line:392, col:4", "selected": false, "exec_coverage": 5.2, "exec_time": 22}, "_Z6workerPv :: for.cond1.i.i.i": {"covered_lcDeps": 23, "loop_speedup": 2.55, "total_time": 427, "dependence_info": {"num_waw_lcdep": 0, "num_control_lcdep": 17, "num_reg_lcdep": 1, "chosen_count": {"reg": {"replicable-stage-remedy": 1}, "ctrl": {"replicable-stage-remedy": 17}, "raw": {"locality-separated-remedy": 3}, "waw": {}, "war": {"mem-ver-remedy": 3}}, "num_war_lcdep": 3, "num_queries": 36, "num_raw_lcdep": 3, "avail_count": {"reg": {"replicable-stage-remedy": 1}, "ctrl": {"replicable-stage-remedy": 17, "ctrl-spec-remedy": 17}, "raw": {"smtx-lamp-remedy": 3, "mem-spec-aa-remedy": 3, "locality-separated-remedy": 3}, "waw": {}, "war": {"mem-ver-remedy": 3, "mem-spec-aa-remedy": 3, "locality-separated-remedy": 3}}}, "total_lcDeps": 24, "loop_stage": "DSWP[P22']", "lcDeps_coverage": 95.83, "debug_info": "filename:HJM_SimPath_Forward_Blocking.cpp, line:65, col:5", "selected": false, "exec_coverage": 27.6, "exec_time": 118}, "_Z6workerPv :: for.cond": {"covered_lcDeps": 9213, "loop_speedup": 16.39, "total_time": 427, "dependence_info": {"num_waw_lcdep": 540, "num_control_lcdep": 7020, "num_reg_lcdep": 1, "chosen_count": {"reg": {"replicable-stage-remedy": 1}, "ctrl": {"replicable-stage-remedy": 390, "ctrl-spec-remedy": 6630}, "raw": {"locality-local-remedy": 873}, "waw": {"locality-local-remedy": 540}, "war": {"mem-ver-remedy": 780}}, "num_war_lcdep": 780, "num_queries": 21316, "num_raw_lcdep": 873, "avail_count": {"reg": {"replicable-stage-remedy": 1}, "ctrl": {"replicable-stage-remedy": 390, "ctrl-spec-remedy": 7020}, "raw": {"locality-local-remedy": 873, "mem-spec-aa-remedy": 873, "smtx-lamp-remedy": 873}, "waw": {"mem-ver-remedy": 540, "locality-local-remedy": 540, "priv-full-overlap-remedy": 9, "mem-spec-aa-remedy": 540}, "war": {"mem-ver-remedy": 780, "locality-local-remedy": 780, "mem-spec-aa-remedy": 780}}}, "total_lcDeps": 9214, "loop_stage": "DSWP[P22']", "lcDeps_coverage": 99.99, "debug_info": "filename:HJM_Securities.cpp, line:89, col:3", "selected": true, "exec_coverage": 100.0, "exec_time": 427}, "_Z6workerPv :: for.cond33.i194.i": {"covered_lcDeps": 0, "loop_speedup": 1.0, "total_time": 427, "dependence_info": {"num_waw_lcdep": 0, "num_control_lcdep": 14, "num_reg_lcdep": 1, "chosen_count": {"reg": {"replicable-stage-remedy": 1}, "ctrl": {"replicable-stage-remedy": 14}, "raw": {}, "waw": {}, "war": {}}, "num_war_lcdep": 0, "num_queries": 9, "num_raw_lcdep": 0, "avail_count": {"reg": {"replicable-stage-remedy": 1}, "ctrl": {"replicable-stage-remedy": 14}, "raw": {}, "waw": {}, "war": {}}}, "total_lcDeps": 15, "loop_stage": "DSWP[P22']", "lcDeps_coverage": 0.0, "debug_info": "filename:HJM.cpp, line:390, col:2", "selected": false, "exec_coverage": 5.4, "exec_time": 23}, "_Z6workerPv :: for.cond10.i144.i": {"covered_lcDeps": 6, "loop_speedup": 1.69, "total_time": 427, "dependence_info": {"num_waw_lcdep": 0, "num_control_lcdep": 6, "num_reg_lcdep": 1, "chosen_count": {"reg": {"replicable-stage-remedy": 1}, "ctrl": {"replicable-stage-remedy": 6}, "raw": {}, "waw": {}, "war": {}}, "num_war_lcdep": 0, "num_queries": 9, "num_raw_lcdep": 0, "avail_count": {"reg": {"replicable-stage-remedy": 1}, "ctrl": {"replicable-stage-remedy": 6, "ctrl-spec-remedy": 6}, "raw": {}, "waw": {}, "war": {}}}, "total_lcDeps": 7, "loop_stage": "DSWP[P22']", "lcDeps_coverage": 85.71, "debug_info": "filename:HJM.cpp, line:383, col:2", "selected": false, "exec_coverage": 10.3, "exec_time": 44}, "_Z6workerPv :: for.cond11.i.i": {"covered_lcDeps": 26, "loop_speedup": 4.0, "total_time": 427, "dependence_info": {"num_waw_lcdep": 2, "num_control_lcdep": 12, "num_reg_lcdep": 1, "chosen_count": {"reg": {"replicable-stage-remedy": 1}, "ctrl": {"replicable-stage-remedy": 12}, "raw": {"locality-separated-remedy": 6}, "waw": {"locality-private-remedy": 2}, "war": {"mem-ver-remedy": 6}}, "num_war_lcdep": 6, "num_queries": 25, "num_raw_lcdep": 6, "avail_count": {"reg": {"replicable-stage-remedy": 1}, "ctrl": {"replicable-stage-remedy": 12, "ctrl-spec-remedy": 12}, "raw": {"smtx-lamp-remedy": 6, "mem-spec-aa-remedy": 6, "locality-separated-remedy": 6}, "waw": {"mem-ver-remedy": 2, "locality-private-remedy": 2, "mem-spec-aa-remedy": 2}, "war": {"mem-ver-remedy": 6, "mem-spec-aa-remedy": 6, "locality-separated-remedy": 6}}}, "total_lcDeps": 27, "loop_stage": "DSWP[P22']", "lcDeps_coverage": 96.3, "debug_info": "filename:HJM_SimPath_Forward_Blocking.cpp, line:103, col:4", "selected": false, "exec_coverage": 5.9, "exec_time": 25}, "_Z6workerPv :: for.cond36.i.i": {"covered_lcDeps": 26, "loop_speedup": 1.0, "total_time": 427, "dependence_info": {"num_waw_lcdep": 0, "num_control_lcdep": 24, "num_reg_lcdep": 2, "chosen_count": {"reg": {"replicable-stage-remedy": 2}, "ctrl": {"replicable-stage-remedy": 8, "ctrl-spec-remedy": 16}, "raw": {"locality-separated-remedy": 1}, "waw": {}, "war": {}}, "num_war_lcdep": 1, "num_queries": 4, "num_raw_lcdep": 1, "avail_count": {"reg": {"replicable-stage-remedy": 2}, "ctrl": {"replicable-stage-remedy": 8, "ctrl-spec-remedy": 24}, "raw": {"smtx-lamp-remedy": 1, "mem-spec-aa-remedy": 1, "locality-separated-remedy": 1}, "waw": {}, "war": {"mem-ver-remedy": 1, "mem-spec-aa-remedy": 1, "locality-separated-remedy": 1}}}, "total_lcDeps": 28, "loop_stage": "DSWP[P21'-S]", "lcDeps_coverage": 92.86, "debug_info": "filename:HJM_SimPath_Forward_Blocking.cpp, line:116, col:9", "selected": false, "exec_coverage": 5.2, "exec_time": 22}, "_Z6workerPv :: for.cond77.i.i": {"covered_lcDeps": 38, "loop_speedup": 3.15, "total_time": 427, "dependence_info": {"num_waw_lcdep": 1, "num_control_lcdep": 22, "num_reg_lcdep": 1, "chosen_count": {"reg": {"replicable-stage-remedy": 1}, "ctrl": {"replicable-stage-remedy": 22}, "raw": {"locality-separated-remedy": 7}, "waw": {}, "war": {}}, "num_war_lcdep": 8, "num_queries": 81, "num_raw_lcdep": 8, "avail_count": {"reg": {"replicable-stage-remedy": 1}, "ctrl": {"replicable-stage-remedy": 22, "ctrl-spec-remedy": 22}, "raw": {"smtx-lamp-remedy": 7, "mem-spec-aa-remedy": 7, "locality-separated-remedy": 7}, "waw": {"mem-ver-remedy": 1}, "war": {"mem-ver-remedy": 8, "mem-spec-aa-remedy": 7, "locality-separated-remedy": 7}}}, "total_lcDeps": 40, "loop_stage": "DSWP[P21'-S]", "lcDeps_coverage": 95.0, "debug_info": "filename:HJM_SimPath_Forward_Blocking.cpp, line:145, col:4", "selected": false, "exec_coverage": 30.7, "exec_time": 131}, "_Z6workerPv :: for.cond5.i.i.i": {"covered_lcDeps": 19, "loop_speedup": 2.1, "total_time": 427, "dependence_info": {"num_waw_lcdep": 0, "num_control_lcdep": 13, "num_reg_lcdep": 1, "chosen_count": {"reg": {"replicable-stage-remedy": 1}, "ctrl": {"replicable-stage-remedy": 13}, "raw": {"locality-separated-remedy": 3}, "waw": {}, "war": {"mem-ver-remedy": 3}}, "num_war_lcdep": 3, "num_queries": 36, "num_raw_lcdep": 3, "avail_count": {"reg": {"replicable-stage-remedy": 1}, "ctrl": {"replicable-stage-remedy": 13, "ctrl-spec-remedy": 13}, "raw": {"smtx-lamp-remedy": 3, "mem-spec-aa-remedy": 3, "locality-separated-remedy": 3}, "waw": {}, "war": {"mem-ver-remedy": 3, "mem-spec-aa-remedy": 3, "locality-separated-remedy": 3}}}, "total_lcDeps": 20, "loop_stage": "DSWP[P22']", "lcDeps_coverage": 95.0, "debug_info": "filename:HJM_SimPath_Forward_Blocking.cpp, line:66, col:7", "selected": false, "exec_coverage": 26.7, "exec_time": 114}, "_Z6workerPv :: for.cond73.i.i": {"covered_lcDeps": 43, "loop_speedup": 4.5, "total_time": 427, "dependence_info": {"num_waw_lcdep": 1, "num_control_lcdep": 26, "num_reg_lcdep": 1, "chosen_count": {"reg": {"replicable-stage-remedy": 1}, "ctrl": {"replicable-stage-remedy": 26}, "raw": {"locality-private-remedy": 1, "locality-separated-remedy": 7}, "waw": {"locality-private-remedy": 1}, "war": {"mem-ver-remedy": 8}}, "num_war_lcdep": 8, "num_queries": 81, "num_raw_lcdep": 8, "avail_count": {"reg": {"replicable-stage-remedy": 1}, "ctrl": {"replicable-stage-remedy": 26, "ctrl-spec-remedy": 26}, "raw": {"smtx-lamp-remedy": 8, "locality-private-remedy": 1, "mem-spec-aa-remedy": 8, "locality-separated-remedy": 7}, "waw": {"mem-ver-remedy": 1, "locality-private-remedy": 1, "mem-spec-aa-remedy": 1}, "war": {"mem-ver-remedy": 8, "locality-private-remedy": 1, "mem-spec-aa-remedy": 8, "locality-separated-remedy": 7}}}, "total_lcDeps": 44, "loop_stage": "DSWP[P22']", "lcDeps_coverage": 97.73, "debug_info": "filename:HJM_SimPath_Forward_Blocking.cpp, line:144, col:2", "selected": false, "exec_coverage": 30.7, "exec_time": 131}, "_Z6workerPv :: for.cond10.i179.i": {"covered_lcDeps": 6, "loop_speedup": 1.53, "total_time": 427, "dependence_info": {"num_waw_lcdep": 0, "num_control_lcdep": 6, "num_reg_lcdep": 1, "chosen_count": {"reg": {"replicable-stage-remedy": 1}, "ctrl": {"replicable-stage-remedy": 6}, "raw": {}, "waw": {}, "war": {}}, "num_war_lcdep": 0, "num_queries": 9, "num_raw_lcdep": 0, "avail_count": {"reg": {"replicable-stage-remedy": 1}, "ctrl": {"replicable-stage-remedy": 6, "ctrl-spec-remedy": 6}, "raw": {}, "waw": {}, "war": {}}}, "total_lcDeps": 7, "loop_stage": "DSWP[P22']", "lcDeps_coverage": 85.71, "debug_info": "filename:HJM.cpp, line:383, col:2", "selected": false, "exec_coverage": 8.4, "exec_time": 36}, "_Z6workerPv :: for.cond.i107.i": {"covered_lcDeps": 30, "loop_speedup": 1.12, "total_time": 427, "dependence_info": {"num_waw_lcdep": 2, "num_control_lcdep": 16, "num_reg_lcdep": 1, "chosen_count": {"reg": {"replicable-stage-remedy": 1}, "ctrl": {"replicable-stage-remedy": 16}, "raw": {"locality-separated-remedy": 6}, "waw": {"locality-private-remedy": 2}, "war": {"mem-ver-remedy": 6}}, "num_war_lcdep": 6, "num_queries": 25, "num_raw_lcdep": 6, "avail_count": {"reg": {"replicable-stage-remedy": 1}, "ctrl": {"replicable-stage-remedy": 16, "ctrl-spec-remedy": 16}, "raw": {"smtx-lamp-remedy": 6, "mem-spec-aa-remedy": 6, "locality-separated-remedy": 6}, "waw": {"mem-ver-remedy": 2, "locality-private-remedy": 2, "mem-spec-aa-remedy": 2}, "war": {"mem-ver-remedy": 6, "mem-spec-aa-remedy": 6, "locality-separated-remedy": 6}}}, "total_lcDeps": 31, "loop_stage": "DSWP[P22']", "lcDeps_coverage": 96.77, "debug_info": "filename:HJM_SimPath_Forward_Blocking.cpp, line:102, col:2", "selected": false, "exec_coverage": 5.9, "exec_time": 25}}, "total_coverage": 100.0, "worker_cnt": 22}}