{"LAMP": true, "Loop": true, "SpecPriv": true, "Edge": true, "Experiment": {"total_coverage": 99.6, "worker_cnt": 22, "speedup": 16.73, "loops": {"kernel_2mm :: for.cond39": {"covered_lcDeps": 8, "exec_coverage": 46.0, "total_time": 235, "debug_info": "filename:2mm.c, line:87, col:7", "dependence_info": {"num_waw_lcdep": 1, "num_war_lcdep": 0, "num_raw_lcdep": 0, "num_control_lcdep": 7, "num_reg_lcdep": 2, "num_queries": 9, "chosen_count": {"reg": {"replicable-stage-remedy": 2}, "waw": {}, "war": {}, "raw": {}, "ctrl": {"replicable-stage-remedy": 7}}, "avail_count": {"reg": {"replicable-stage-remedy": 2}, "waw": {"priv-full-overlap-remedy": 1, "locality-private-remedy": 1, "mem-ver-remedy": 1, "mem-spec-aa-remedy": 1}, "war": {}, "raw": {}, "ctrl": {"replicable-stage-remedy": 7, "ctrl-spec-remedy": 7}}}, "total_lcDeps": 10, "exec_time": 108, "lcDeps_coverage": 80.0}, "kernel_2mm :: for.cond1": {"covered_lcDeps": 12, "loop_speedup": 7.19, "exec_coverage": 52.8, "total_time": 235, "debug_info": "filename:2mm.c, line:77, col:5", "loop_stage": "DSWP[P22']", "dependence_info": {"num_waw_lcdep": 0, "num_war_lcdep": 0, "num_raw_lcdep": 0, "num_control_lcdep": 12, "num_reg_lcdep": 1, "num_queries": 16, "chosen_count": {"reg": {"replicable-stage-remedy": 1}, "waw": {}, "war": {}, "raw": {}, "ctrl": {"replicable-stage-remedy": 12}}, "avail_count": {"reg": {"replicable-stage-remedy": 1}, "waw": {}, "war": {}, "raw": {}, "ctrl": {"replicable-stage-remedy": 12, "ctrl-spec-remedy": 12}}}, "total_lcDeps": 13, "selected": false, "exec_time": 124, "lcDeps_coverage": 92.31}, "kernel_2mm :: for.cond6": {"covered_lcDeps": 8, "exec_coverage": 52.3, "total_time": 235, "debug_info": "filename:2mm.c, line:80, col:7", "dependence_info": {"num_waw_lcdep": 1, "num_war_lcdep": 0, "num_raw_lcdep": 0, "num_control_lcdep": 7, "num_reg_lcdep": 2, "num_queries": 9, "chosen_count": {"reg": {"replicable-stage-remedy": 2}, "waw": {}, "war": {}, "raw": {}, "ctrl": {"replicable-stage-remedy": 7}}, "avail_count": {"reg": {"replicable-stage-remedy": 2}, "waw": {"priv-full-overlap-remedy": 1, "locality-private-remedy": 1, "mem-ver-remedy": 1, "mem-spec-aa-remedy": 1}, "war": {}, "raw": {}, "ctrl": {"replicable-stage-remedy": 7, "ctrl-spec-remedy": 7}}}, "total_lcDeps": 10, "exec_time": 123, "lcDeps_coverage": 80.0}, "kernel_2mm :: for.cond31": {"covered_lcDeps": 13, "loop_speedup": 6.6, "exec_coverage": 46.8, "total_time": 235, "debug_info": "filename:2mm.c, line:84, col:5", "loop_stage": "DSWP[P22']", "dependence_info": {"num_waw_lcdep": 0, "num_war_lcdep": 0, "num_raw_lcdep": 0, "num_control_lcdep": 13, "num_reg_lcdep": 1, "num_queries": 25, "chosen_count": {"reg": {"replicable-stage-remedy": 1}, "waw": {}, "war": {}, "raw": {}, "ctrl": {"replicable-stage-remedy": 13}}, "avail_count": {"reg": {"replicable-stage-remedy": 1}, "waw": {}, "war": {}, "raw": {}, "ctrl": {"replicable-stage-remedy": 13, "ctrl-spec-remedy": 13}}}, "total_lcDeps": 14, "selected": false, "exec_time": 110, "lcDeps_coverage": 92.86}, "kernel_2mm :: for.cond": {"covered_lcDeps": 16, "loop_speedup": 18.08, "exec_coverage": 52.8, "total_time": 235, "debug_info": "filename:2mm.c, line:76, col:3", "loop_stage": "DSWP[P22']", "dependence_info": {"num_waw_lcdep": 0, "num_war_lcdep": 0, "num_raw_lcdep": 0, "num_control_lcdep": 16, "num_reg_lcdep": 1, "num_queries": 16, "chosen_count": {"reg": {"replicable-stage-remedy": 1}, "waw": {}, "war": {}, "raw": {}, "ctrl": {"replicable-stage-remedy": 16}}, "avail_count": {"reg": {"replicable-stage-remedy": 1}, "waw": {}, "war": {}, "raw": {}, "ctrl": {"replicable-stage-remedy": 16, "ctrl-spec-remedy": 16}}}, "total_lcDeps": 17, "selected": true, "exec_time": 124, "lcDeps_coverage": 94.12}, "kernel_2mm :: for.cond28": {"covered_lcDeps": 17, "loop_speedup": 17.77, "exec_coverage": 46.8, "total_time": 235, "debug_info": "filename:2mm.c, line:83, col:3", "loop_stage": "DSWP[P22']", "dependence_info": {"num_waw_lcdep": 0, "num_war_lcdep": 0, "num_raw_lcdep": 0, "num_control_lcdep": 17, "num_reg_lcdep": 1, "num_queries": 25, "chosen_count": {"reg": {"replicable-stage-remedy": 1}, "waw": {}, "war": {}, "raw": {}, "ctrl": {"replicable-stage-remedy": 17}}, "avail_count": {"reg": {"replicable-stage-remedy": 1}, "waw": {}, "war": {}, "raw": {}, "ctrl": {"replicable-stage-remedy": 17, "ctrl-spec-remedy": 17}}}, "total_lcDeps": 18, "selected": true, "exec_time": 110, "lcDeps_coverage": 94.44}}}, "SLAMP": true}